{
    "configurations": [
        {
            "name": "Linux",
            "includePath": [
                "${workspaceFolder}/**",
                "/usr/include/SDL2/"
            ],
            "defines": [],
            "compilerPath": "/usr/bin/gcc",
            "cStandard": "c17",
            "cppStandard": "gnu++14",
            "intelliSenseMode": "gcc-x64",
            "configurationProvider": "ms-vscode.makefile-tools"
        },
        {
            "name": "standard",
            "includePath": [
                "${workspaceFolder}/**"
            ],
            "defines": [],
            "compilerPath": "/usr/local/bin/clang",
            "cStandard": "c17",
            "cppStandard": "c++14",
            "intelliSenseMode": "linux-clang-x64"
        }
    ],
    "version": 4
}